cloudmesh_piazza/__init__.py
cloudmesh_piazza/cm_piazza_api.py
cloudmesh_piazza/piazza.py
cloudmesh_piazza/version.py
cloudmesh_piazza-0.0.7.dist-info/DESCRIPTION.rst
cloudmesh_piazza-0.0.7.dist-info/METADATA
cloudmesh_piazza-0.0.7.dist-info/RECORD
cloudmesh_piazza-0.0.7.dist-info/WHEEL
cloudmesh_piazza-0.0.7.dist-info/entry_points.txt
cloudmesh_piazza-0.0.7.dist-info/metadata.json
cloudmesh_piazza-0.0.7.dist-info/pbr.json
cloudmesh_piazza-0.0.7.dist-info/top_level.txt
