Metadata-Version: 2.0
Name: cloudmesh-piazza
Version: 0.0.7
Summary: Command line client for Piazza
Home-page: https://gitlab.com/cloudmesh_fall2016/piazza
Author: Gregor von Laszewski, Tim Whitson
Author-email: laszewski@gmail.com
License: Apache 2.0
Platform: any
Classifier: Programming Language :: Python
Classifier: Development Status :: 3 - Alpha
Classifier: Natural Language :: English
Classifier: Environment :: Web Environment
Classifier: Intended Audience :: Developers
Classifier: License :: OSI Approved :: MIT License
Classifier: Operating System :: OS Independent
Classifier: Programming Language :: Python :: 2.7
Classifier: Programming Language :: Python :: 3.3
Classifier: Topic :: Software Development :: Libraries :: Python Modules
Requires-Dist: docopt
Requires-Dist: pyyaml
Requires-Dist: requests
